OpenCA/CA.py
OpenCA/CAExceptions.py
OpenCA/CSR.py
OpenCA/Signing.py
OpenCA/Utils.py
OpenCA/__init__.py
OpenCA/model.py
OpenCA-0.1.1.dist-info/DESCRIPTION.rst
OpenCA-0.1.1.dist-info/METADATA
OpenCA-0.1.1.dist-info/RECORD
OpenCA-0.1.1.dist-info/WHEEL
OpenCA-0.1.1.dist-info/metadata.json
OpenCA-0.1.1.dist-info/top_level.txt
