Metadata-Version: 2.0
Name: OpenCA
Version: 0.1.1
Summary: A library to easily manage Certification Authorities based on OpenSSL
Home-page: https://github.com/ash2shukla/OpenCA
Author: Ashish Shukla
Author-email: ash2shukla@gmail.com
License: MIT
Keywords: CA,pyOpenSSL,OpenSSL
Platform: UNKNOWN
Requires-Dist: cryptography
Requires-Dist: pyOpenSSL
Requires-Dist: sqlalchemy
